kinfer_sim/__init__.py
kinfer_sim/provider.py
kinfer_sim/py.typed
kinfer_sim/server.py
kinfer_sim/simulator.py
kinfer_sim/viewer.py
kinfer_sim-0.0.1.data/scripts/kinfer-sim
kinfer_sim-0.0.1.dist-info/licenses/LICENSE
kinfer_sim-0.0.1.dist-info/METADATA
kinfer_sim-0.0.1.dist-info/WHEEL
kinfer_sim-0.0.1.dist-info/top_level.txt
kinfer_sim-0.0.1.dist-info/RECORD
